{
  "analysis_date": "2026-06-17T21:27:21.030678",
  "version": "v2_enhanced",
  "strategies_tested": 16,
  "stocks": {
    "300179": {
      "strategy": "Turtle_20x10_DoubleLoss",
      "total_return": 1.2234060373541804,
      "ann_return": 0.14978401032646493,
      "sharpe": 5.37501130974527,
      "max_drawdown": -0.04548504746524004,
      "calmar": 3.293038452711978,
      "win_rate": 0.6226415094339622,
      "num_trades": 53,
      "avg_win_pct": 3.2390671959748216,
      "avg_loss_pct": -1.1640709611172573,
      "profit_factor": 4.5911813384889575,
      "total_years": 5.724845995893224,
      "stop_hits": 53,
      "signal_exits": 0,
      "params": {
        "stop_type": "atr",
        "atr_mult": 2.0,
        "chan_period": 20,
        "double_loss": true
      },
      "score": 0.8156,
      "stock_type": "高波动/题材型",
      "price_volatility": 0.5795878254398839,
      "avg_daily_amount": 1.3760184336321835
    },
    "002222": {
      "strategy": "Turtle_20x10_DoubleLoss",
      "total_return": 0.832135432634824,
      "ann_return": 0.11150324052207816,
      "sharpe": 4.9980742392051365,
      "max_drawdown": -0.06347613365924244,
      "calmar": 1.756616764352073,
      "win_rate": 0.4696969696969697,
      "num_trades": 66,
      "avg_win_pct": 3.0575861615328104,
      "avg_loss_pct": -0.9054240110053415,
      "profit_factor": 2.9910270880323946,
      "total_years": 5.727583846680356,
      "stop_hits": 66,
      "signal_exits": 0,
      "params": {
        "stop_type": "atr",
        "atr_mult": 2.0,
        "chan_period": 20,
        "double_loss": true
      },
      "score": 0.7187,
      "stock_type": "高波动/题材型",
      "price_volatility": 0.46755623152251563,
      "avg_daily_amount": 3.385312886628352
    },
    "688599": {
      "strategy": "Turtle_20x10_DoubleLoss",
      "total_return": 0.6991360192152285,
      "ann_return": 0.1319711512413111,
      "sharpe": 5.561755358322292,
      "max_drawdown": -0.06990775051317365,
      "calmar": 1.8877899842656505,
      "win_rate": 0.625,
      "num_trades": 32,
      "avg_win_pct": 3.7098622095200025,
      "avg_loss_pct": -1.5294844580571543,
      "profit_factor": 4.042606415489504,
      "total_years": 4.276522929500342,
      "stop_hits": 32,
      "signal_exits": 0,
      "params": {
        "stop_type": "atr",
        "atr_mult": 2.0,
        "chan_period": 20,
        "double_loss": true
      },
      "score": 0.7793,
      "stock_type": "高波动/题材型",
      "price_volatility": 0.5816599718031438,
      "avg_daily_amount": 7.574469761760343
    },
    "300690": {
      "strategy": "Turtle_20x10_DoubleLoss",
      "total_return": 1.775162953287071,
      "ann_return": 0.19507558279175607,
      "sharpe": 5.853236064299013,
      "max_drawdown": -0.04897047739853402,
      "calmar": 3.9835344304320763,
      "win_rate": 0.58,
      "num_trades": 50,
      "avg_win_pct": 4.609035557020537,
      "avg_loss_pct": -1.208342939868295,
      "profit_factor": 5.2674273307339705,
      "total_years": 5.727583846680356,
      "stop_hits": 50,
      "signal_exits": 0,
      "params": {
        "stop_type": "atr",
        "atr_mult": 2.0,
        "chan_period": 20,
        "double_loss": true
      },
      "score": 0.8595,
      "stock_type": "高波动/题材型",
      "price_volatility": 0.5979565392105154,
      "avg_daily_amount": 1.2726295492492332
    },
    "301091": {
      "strategy": "Turtle_20x10_DoubleLoss",
      "total_return": 0.6945613546715697,
      "ann_return": 0.1997112402560226,
      "sharpe": 5.318096788376004,
      "max_drawdown": -0.07797829128767045,
      "calmar": 2.561113317029043,
      "win_rate": 0.5769230769230769,
      "num_trades": 26,
      "avg_win_pct": 5.299206202288679,
      "avg_loss_pct": -2.0886658278464614,
      "profit_factor": 3.4597158528221015,
      "total_years": 2.8966461327857633,
      "stop_hits": 26,
      "signal_exits": 0,
      "params": {
        "stop_type": "atr",
        "atr_mult": 2.0,
        "chan_period": 20,
        "double_loss": true
      },
      "score": 0.8471,
      "stock_type": "高波动/题材型",
      "price_volatility": 0.7591173113518833,
      "avg_daily_amount": 2.5298986314720504
    },
    "603322": {
      "strategy": "Turtle_20x10_DoubleLoss",
      "total_return": 1.7367092080476771,
      "ann_return": 0.19226795567367527,
      "sharpe": 7.795367856080033,
      "max_drawdown": -0.0590277848389226,
      "calmar": 3.2572449770619687,
      "win_rate": 0.660377358490566,
      "num_trades": 53,
      "avg_win_pct": 3.7854698214729345,
      "avg_loss_pct": -1.5681622081363662,
      "profit_factor": 4.693797443775073,
      "total_years": 5.724845995893224,
      "stop_hits": 53,
      "signal_exits": 0,
      "params": {
        "stop_type": "atr",
        "atr_mult": 2.0,
        "chan_period": 20,
        "double_loss": true
      },
      "score": 0.87,
      "stock_type": "高波动/题材型",
      "price_volatility": 0.5501281607944978,
      "avg_daily_amount": 1.650417599805226
    },
    "300102": {
      "strategy": "Turtle_20x10_DoubleLoss",
      "total_return": 4.360008636446261,
      "ann_return": 0.3408141274692824,
      "sharpe": 4.641027340512943,
      "max_drawdown": -0.050287264150943305,
      "calmar": 6.777344785476648,
      "win_rate": 0.660377358490566,
      "num_trades": 53,
      "avg_win_pct": 5.97280833115059,
      "avg_loss_pct": -1.2288197486704426,
      "profit_factor": 9.451177839388683,
      "total_years": 5.724845995893224,
      "stop_hits": 53,
      "signal_exits": 0,
      "params": {
        "stop_type": "atr",
        "atr_mult": 2.0,
        "chan_period": 20,
        "double_loss": true
      },
      "score": 0.8849,
      "stock_type": "高波动/题材型",
      "price_volatility": 0.5995766298794639,
      "avg_daily_amount": 2.67988041751126
    },
    "002389": {
      "strategy": "Turtle_20x10_DoubleLoss",
      "total_return": 1.2928299802527694,
      "ann_return": 0.15589570885885928,
      "sharpe": 5.209071663187621,
      "max_drawdown": -0.05810390853992678,
      "calmar": 2.683050293453731,
      "win_rate": 0.5517241379310345,
      "num_trades": 58,
      "avg_win_pct": 3.526109386423436,
      "avg_loss_pct": -0.9959085518249979,
      "profit_factor": 4.357656061074908,
      "total_years": 5.727583846680356,
      "stop_hits": 58,
      "signal_exits": 0,
      "params": {
        "stop_type": "atr",
        "atr_mult": 2.0,
        "chan_period": 20,
        "double_loss": true
      },
      "score": 0.7979,
      "stock_type": "高波动/题材型",
      "price_volatility": 0.47668247202040165,
      "avg_daily_amount": 4.205455982164118
    },
    "300058": {
      "strategy": "Turtle_20x10_DoubleLoss",
      "total_return": 1.5404258083735205,
      "ann_return": 0.1767768680380113,
      "sharpe": 6.504686888030189,
      "max_drawdown": -0.0263693422318425,
      "calmar": 6.703878560328405,
      "win_rate": 0.5833333333333334,
      "num_trades": 48,
      "avg_win_pct": 4.209554614881683,
      "avg_loss_pct": -0.9981271036977829,
      "profit_factor": 5.9044348550410435,
      "total_years": 5.727583846680356,
      "stop_hits": 48,
      "signal_exits": 0,
      "params": {
        "stop_type": "atr",
        "atr_mult": 2.0,
        "chan_period": 20,
        "double_loss": true
      },
      "score": 0.851,
      "stock_type": "高波动/题材型",
      "price_volatility": 0.5852112284194089,
      "avg_daily_amount": 6.704963158308597
    },
    "603901": {
      "strategy": "Turtle_20x10_DoubleLoss",
      "total_return": 1.0640680482524614,
      "ann_return": 0.13487708369353957,
      "sharpe": 4.3737031816178575,
      "max_drawdown": -0.16275661128182567,
      "calmar": 0.828704177552514,
      "win_rate": 0.5,
      "num_trades": 54,
      "avg_win_pct": 4.152846243228128,
      "avg_loss_pct": -1.2935435320421902,
      "profit_factor": 3.210441813791758,
      "total_years": 5.727583846680356,
      "stop_hits": 54,
      "signal_exits": 0,
      "params": {
        "stop_type": "atr",
        "atr_mult": 2.0,
        "chan_period": 20,
        "double_loss": true
      },
      "score": 0.6959,
      "stock_type": "高波动/题材型",
      "price_volatility": 0.46767950652462426,
      "avg_daily_amount": 0.7182624299799296
    },
    "603667": {
      "strategy": "Turtle_20x10_DoubleLoss",
      "total_return": 0.9156226787365134,
      "ann_return": 0.12030611491781706,
      "sharpe": 3.341287541614865,
      "max_drawdown": -0.11062431949734078,
      "calmar": 1.0875195930195893,
      "win_rate": 0.5862068965517241,
      "num_trades": 58,
      "avg_win_pct": 3.3435034399810473,
      "avg_loss_pct": -1.7822379625563285,
      "profit_factor": 2.6576865563521954,
      "total_years": 5.722108145106092,
      "stop_hits": 58,
      "signal_exits": 0,
      "params": {
        "stop_type": "atr",
        "atr_mult": 2.0,
        "chan_period": 20,
        "double_loss": true
      },
      "score": 0.7306,
      "stock_type": "高波动/题材型",
      "price_volatility": 0.5663952793356205,
      "avg_daily_amount": 2.531042655025059
    },
    "603286": {
      "strategy": "Turtle_20x10_DoubleLoss",
      "total_return": 2.515304232219549,
      "ann_return": 0.24807813207805585,
      "sharpe": 5.438482093491924,
      "max_drawdown": -0.050031093793153326,
      "calmar": 4.958479083101816,
      "win_rate": 0.559322033898305,
      "num_trades": 59,
      "avg_win_pct": 4.727768042503947,
      "avg_loss_pct": -0.8704798373484889,
      "profit_factor": 6.893472326263237,
      "total_years": 5.672826830937714,
      "stop_hits": 59,
      "signal_exits": 0,
      "params": {
        "stop_type": "atr",
        "atr_mult": 2.0,
        "chan_period": 20,
        "double_loss": true
      },
      "score": 0.8598,
      "stock_type": "高波动/题材型",
      "price_volatility": 0.5149509257441289,
      "avg_daily_amount": 0.8838286366215056
    },
    "600118": {
      "strategy": "Turtle_20x10_DoubleLoss",
      "total_return": 0.7785048769577192,
      "ann_return": 0.10580593058529653,
      "sharpe": 6.794241695405779,
      "max_drawdown": -0.06047755083055804,
      "calmar": 1.749507530186474,
      "win_rate": 0.6511627906976745,
      "num_trades": 43,
      "avg_win_pct": 2.6170808269146186,
      "avg_loss_pct": -0.9294917053145955,
      "profit_factor": 5.255794662439197,
      "total_years": 5.724845995893224,
      "stop_hits": 43,
      "signal_exits": 0,
      "params": {
        "stop_type": "atr",
        "atr_mult": 2.0,
        "chan_period": 20,
        "double_loss": true
      },
      "score": 0.7588,
      "stock_type": "中等波动/趋势型",
      "price_volatility": 0.39453857851080726,
      "avg_daily_amount": 5.119175824788249
    }
  },
  "ranking": [
    "300102",
    "603322",
    "603286",
    "300690",
    "300058",
    "301091",
    "300179",
    "002389",
    "688599",
    "600118",
    "603667",
    "002222",
    "603901"
  ]
}