[
  {
    "params": [
      5,
      21,
      3,
      10,
      3
    ],
    "period": [
      "2010-W01",
      "2018-W52"
    ],
    "result": {
      "annual": 4.0227475808681135,
      "sharpe": 0.24342602320872686,
      "max_dd": -12.485209565750498
    }
  },
  {
    "params": [
      5,
      21,
      3,
      10,
      3
    ],
    "period": [
      "2019-W01",
      "2026-W18"
    ],
    "result": {
      "annual": 30.385094140674962,
      "sharpe": 1.4138078996092163,
      "max_dd": -18.94736664721899
    }
  },
  {
    "params": [
      5,
      21,
      4,
      10,
      3
    ],
    "period": [
      "2010-W01",
      "2018-W52"
    ],
    "result": {
      "annual": 2.422681309828656,
      "sharpe": 0.09015226270709549,
      "max_dd": -17.153941031172714
    }
  },
  {
    "params": [
      5,
      21,
      4,
      10,
      3
    ],
    "period": [
      "2019-W01",
      "2026-W18"
    ],
    "result": {
      "annual": 33.74641674943102,
      "sharpe": 1.5036271476890515,
      "max_dd": -16.128889511192224
    }
  },
  {
    "params": [
      5,
      21,
      5,
      10,
      3
    ],
    "period": [
      "2010-W01",
      "2018-W52"
    ],
    "result": {
      "annual": 2.1601182237176664,
      "sharpe": 0.06664229108295426,
      "max_dd": -18.632111816204556
    }
  },
  {
    "params": [
      5,
      21,
      5,
      10,
      3
    ],
    "period": [
      "2019-W01",
      "2026-W18"
    ],
    "result": {
      "annual": 22.31838095066001,
      "sharpe": 1.0172705189391693,
      "max_dd": -24.16406294662896
    }
  },
  {
    "params": [
      5,
      21,
      3,
      5,
      3
    ],
    "period": [
      "2010-W01",
      "2018-W52"
    ],
    "result": {
      "annual": 1.214598403682987,
      "sharpe": -0.1339738013707685,
      "max_dd": -11.205625267196883
    }
  },
  {
    "params": [
      5,
      21,
      3,
      5,
      3
    ],
    "period": [
      "2019-W01",
      "2026-W18"
    ],
    "result": {
      "annual": 15.632878368865466,
      "sharpe": 0.9237290850381888,
      "max_dd": -25.03184558796757
    }
  },
  {
    "params": [
      5,
      21,
      3,
      15,
      3
    ],
    "period": [
      "2010-W01",
      "2018-W52"
    ],
    "result": {
      "annual": 1.7607032611935747,
      "sharpe": 0.03365871840477196,
      "max_dd": -19.45370840359636
    }
  },
  {
    "params": [
      5,
      21,
      3,
      15,
      3
    ],
    "period": [
      "2019-W01",
      "2026-W18"
    ],
    "result": {
      "annual": 35.582095140653806,
      "sharpe": 1.4471601274084596,
      "max_dd": -27.536291800068714
    }
  },
  {
    "params": [
      5,
      21,
      2,
      10,
      3
    ],
    "period": [
      "2010-W01",
      "2018-W52"
    ],
    "result": {
      "annual": 2.9125557628054466,
      "sharpe": 0.14537010807173606,
      "max_dd": -13.236660437269254
    }
  },
  {
    "params": [
      5,
      21,
      2,
      10,
      3
    ],
    "period": [
      "2019-W01",
      "2026-W18"
    ],
    "result": {
      "annual": 28.163054977878033,
      "sharpe": 1.3686072697360379,
      "max_dd": -18.569255201405234
    }
  },
  {
    "params": [
      5,
      21,
      2,
      15,
      3
    ],
    "period": [
      "2010-W01",
      "2018-W52"
    ],
    "result": {
      "annual": 0.6144906126266614,
      "sharpe": -0.08707283026128904,
      "max_dd": -17.81285185265613
    }
  },
  {
    "params": [
      5,
      21,
      2,
      15,
      3
    ],
    "period": [
      "2019-W01",
      "2026-W18"
    ],
    "result": {
      "annual": 28.41822863483925,
      "sharpe": 1.2384722395856769,
      "max_dd": -32.43129546326049
    }
  },
  {
    "params": [
      3,
      13,
      3,
      10,
      3
    ],
    "period": [
      "2010-W01",
      "2018-W52"
    ],
    "result": {
      "annual": 0.18219224930606792,
      "sharpe": -0.10236792617609458,
      "max_dd": -23.538152060489303
    }
  },
  {
    "params": [
      3,
      13,
      3,
      10,
      3
    ],
    "period": [
      "2019-W01",
      "2026-W18"
    ],
    "result": {
      "annual": 24.095422902414,
      "sharpe": 1.0813344216576712,
      "max_dd": -28.642481988089287
    }
  },
  {
    "params": [
      10,
      30,
      3,
      10,
      3
    ],
    "period": [
      "2010-W01",
      "2018-W52"
    ],
    "result": {
      "annual": -3.412593645389561,
      "sharpe": -0.8343155389052803,
      "max_dd": -36.3214242443951
    }
  },
  {
    "params": [
      10,
      30,
      3,
      10,
      3
    ],
    "period": [
      "2019-W01",
      "2026-W18"
    ],
    "result": {
      "annual": 14.610212440726622,
      "sharpe": 0.7848304979857801,
      "max_dd": -32.23260334819831
    }
  },
  {
    "params": [
      5,
      21,
      3,
      10,
      2
    ],
    "period": [
      "2010-W01",
      "2018-W52"
    ],
    "result": {
      "annual": 4.58119040831535,
      "sharpe": 0.2641879739644192,
      "max_dd": -15.00804372516079
    }
  },
  {
    "params": [
      5,
      21,
      3,
      10,
      2
    ],
    "period": [
      "2019-W01",
      "2026-W18"
    ],
    "result": {
      "annual": 38.21143091795343,
      "sharpe": 1.5755584418617476,
      "max_dd": -20.893642590293215
    }
  }
]